ckanext_resource_docs-0.4.3-py3.10-nspkg.pth
ckanext/resource_docs/__init__.py
ckanext/resource_docs/config.py
ckanext/resource_docs/helpers.py
ckanext/resource_docs/interfaces.py
ckanext/resource_docs/model.py
ckanext/resource_docs/plugin.py
ckanext/resource_docs/utils.py
ckanext/resource_docs/views.py
ckanext/resource_docs/assets/webassets.yml
ckanext/resource_docs/assets/css/styles.css
ckanext/resource_docs/assets/css/vendor/jsoneditor.min.css
ckanext/resource_docs/assets/js/rdocs-jsoneditor-docs.js
ckanext/resource_docs/assets/js/vendor/jsoneditor.min.js
ckanext/resource_docs/logic/__init__.py
ckanext/resource_docs/logic/action.py
ckanext/resource_docs/logic/auth.py
ckanext/resource_docs/logic/schema.py
ckanext/resource_docs/migration/resource_docs/alembic.ini
ckanext/resource_docs/migration/resource_docs/env.py
ckanext/resource_docs/migration/resource_docs/script.py.mako
ckanext/resource_docs/migration/resource_docs/versions/ddef6e042fbe_create_resource_docs_table.py
ckanext/resource_docs/templates/page.html
ckanext/resource_docs/templates/package/resource_edit_base.html
ckanext/resource_docs/templates/package/resource_read.html
ckanext/resource_docs/templates/resource_docs/edit.html
ckanext/resource_docs/templates/resource_docs/resource_docs_view.html
ckanext/resource_docs/templates/resource_docs/view/kv-table.html
ckanext/resource_docs/templates/resource_docs/view/list-table.html
ckanext/resource_docs/templates/resource_docs/view/render.html
ckanext/resource_docs/templates/resource_docs/view/sequence.html
ckanext/resource_docs/templates/resource_docs/view/value.html
ckanext/resource_docs/tests/__init__.py
ckanext/resource_docs/tests/conftest.py
ckanext/resource_docs/tests/test_action.py
ckanext/resource_docs/tests/test_auth.py
ckanext/resource_docs/tests/test_helpers.py
ckanext/resource_docs/tests/test_model.py
ckanext/resource_docs/tests/test_utils.py
ckanext/resource_docs/tests/test_views.py
ckanext_resource_docs-0.4.3.dist-info/licenses/LICENSE
ckanext_resource_docs-0.4.3.dist-info/METADATA
ckanext_resource_docs-0.4.3.dist-info/WHEEL
ckanext_resource_docs-0.4.3.dist-info/entry_points.txt
ckanext_resource_docs-0.4.3.dist-info/namespace_packages.txt
ckanext_resource_docs-0.4.3.dist-info/top_level.txt
ckanext_resource_docs-0.4.3.dist-info/RECORD
