Metadata-Version: 2.4
Name: ckanext-resource-docs
Version: 0.4.3
Summary: A CKAN extension that lets you attach a flexible, schema-free data dictionary (“resource documentation”) to any resource, not just Datastore-backed ones.
Author-email: Oleksandr Cherniavskiy <mutantsan@gmail.com>
License: AGPL
Project-URL: Homepage, https://github.com/DataShades/ckanext-resource-docs
Keywords: CKAN
Classifier: Development Status :: 4 - Beta
Classifier: License :: OSI Approved :: GNU Affero General Public License v3 or later (AGPLv3+)
Classifier: Programming Language :: Python :: 3.8
Classifier: Programming Language :: Python :: 3.9
Classifier: Programming Language :: Python :: 3.10
License-File: LICENSE
Requires-Dist: jsonschema<5.0.0,>=4.25.0
Dynamic: license-file
